{
  "version": "7",
  "dialect": "mysql",
  "entries": [
    {
      "idx": 0,
      "version": "5",
      "when": 1768421055674,
      "tag": "0000_magenta_steel_serpent",
      "breakpoints": true
    },
    {
      "idx": 1,
      "version": "5",
      "when": 1768421257943,
      "tag": "0001_crazy_ultimates",
      "breakpoints": true
    },
    {
      "idx": 2,
      "version": "5",
      "when": 1768421675596,
      "tag": "0002_futuristic_black_crow",
      "breakpoints": true
    },
    {
      "idx": 3,
      "version": "5",
      "when": 1768429843297,
      "tag": "0003_petite_thunderbolt",
      "breakpoints": true
    }
  ]
}